seedlib/__init__.py
seedlib/main.py
seedlib-0.1.dist-info/DESCRIPTION.rst
seedlib-0.1.dist-info/METADATA
seedlib-0.1.dist-info/RECORD
seedlib-0.1.dist-info/WHEEL
seedlib-0.1.dist-info/metadata.json
seedlib-0.1.dist-info/top_level.txt
